{
    "id": "nali",
    "ver": "0.8.1",
    "date": "2023-12-11",
    "arch": {
        "32bit": "https://github.com/zu1k/nali/releases/download/v0.8.1/nali-windows-386-v0.8.1.zip",
        "64bit": "https://github.com/zu1k/nali/releases/download/v0.8.1/nali-windows-amd64-v0.8.1.zip"
    },
    "sha256": {
        "32bit": "9c907563018e4ef070225d8eb06d5c57d804bd6c3ab6a7ff1da7ec9b243bd43d",
        "64bit": "a0b1e1c157431708446b9d92ebd4690ab793012a408dfa0b76e02644d50b65c2"
    },
    "changelog": "https://github.com/zu1k/nali/releases/latest",
    "bin": {
        "32bit": [
            [
                "nali-windows-386.exe",
                "nali"
            ]
        ],
        "64bit": [
            [
                "nali-windows-amd64.exe",
                "nali"
            ]
        ]
    }
}